<?xml version="1.0" encoding="UTF-8"?>

<Body> 
	<Title>京珠高速韶关段 高速大巴撞货车17人死 (27日头条)</Title>  
	<ReportTime type="absTime">2006-8-28 9:21:11</ReportTime>  
	<Content> 
		<Paragraph> 
			<Sentence> 
				<Event eid="e1"> 
					<Time type="relTime" tid="t1">昨天凌晨1时10分左右</Time>， 
					<Location lid="l1">京珠北高速公路乳源东田段</Location>北行方向发生特大 
					<Denoter type="emergency" did="d1">交通事故</Denoter> 
				</Event>， 
				<Event eid="e2">一辆高速行驶的 
					<Object oid="o2">大客车</Object>追尾 
					<Denoter type="action" did="d2">撞上</Denoter>故障 
					<Object oid="o2">大货车</Object> 
				</Event>，共造成 
				<Event eid="e3"> 
					<Participant oid="o3">17人</Participant>  
					<Denoter type="stateChange" did="d3">死亡</Denoter> 
				</Event>、 
				<Event eid="e4"> 
					<Participant oid="o4">1人</Participant>  
					<Denoter type="stateChange" did="d4">重伤</Denoter> 
				</Event>、 
				<Event eid="e5"> 
					<Participant oid="o5">4人</Participant>  
					<Denoter type="stateChange" did="d5">轻伤</Denoter> 
				</Event>， 
				<Event eid="e6"> 
					<Participant oid="o6">28人</Participant>  
					<Denoter type="stateChange" did="d6">轻微伤</Denoter> 
				</Event>。
			</Sentence> 
		</Paragraph>  
		<Paragraph> 
			<Sentence> 
				<Event eid="e7"> 
					<Time type="relTime" tid="t7">目前</Time>  
					<Participant oid="o7">大客车司机</Participant>已被 
					<Participant sid="s7">警方</Participant>  
					<Denoter type="operation" did="d7">控制</Denoter> 
				</Event>。
			</Sentence>  
			<Sentence> 
				<Event eid="e8"> 
					<Time type="relTime" tid="t8">昨天凌晨1时10分左右</Time>， 
					<Location lid="l8">京珠北高速公路75km+300m北行方向</Location>发生一辆高速行驶的大客车追尾撞上故障大货车的特大 
					<Denoter type="emergency" did="d8">交通事故</Denoter> 
				</Event>，共造成 
				<Event eid="e9"> 
					<Participant oid="o9">17人</Participant>  
					<Denoter type="stateChange" did="d9">死亡</Denoter> 
				</Event>、 
				<Event eid="e10"> 
					<Participant oid="o10">1人</Participant>  
					<Denoter type="stateChange" did="d10">重伤</Denoter> 
				</Event>、 
				<Event eid="e11"> 
					<Participant oid="o11">4人</Participant>  
					<Denoter type="stateChange" did="d11">轻伤</Denoter> 
				</Event>。
			</Sentence>  
			<Sentence>根据统计，受伤者中最小的刘玉华年仅15岁，最大的贾王今年59岁。</Sentence> 
		</Paragraph> 
	</Content>  
	<eRelation relType="Causal" cause_eid="e2" effect_eid="e3"/>  
	<eRelation relType="Causal" cause_eid="e2" effect_eid="e4"/>  
	<eRelation relType="Causal" cause_eid="e2" effect_eid="e5"/>  
	<eRelation relType="Causal" cause_eid="e2" effect_eid="e6"/>  
	<eRelation relType="Causal" cause_eid="e8" effect_eid="e9"/>  
	<eRelation relType="Causal" cause_eid="e8" effect_eid="e10"/>  
	<eRelation relType="Causal" cause_eid="e8" effect_eid="e11"/> 
</Body>
