<?xml version="1.0" encoding="UTF-8"?>

<Body> 
	<Title>青海发生6.3级地震 震区人口密度低尚无人员伤亡</Title>  
	<ReportTime type="absTime">2008年11月10日</ReportTime>  
	<Content> 
		<Paragraph> 
			<Sentence>
				<Event type="thoughtevent" eid="e1">
					<Participant sid="s1">新华社西宁</Participant>
					<Time tid="t1" type="relTime">１１月１０日</Time>
					<Denoter did="d1" type="statement">电</Denoter>
				</Event>
			</Sentence>（记者马勇、侯德强） 
			<Sentence> 
				<Event eid="e2" type="thoughtevent">据青
					<Participant sid="s2">海省地震台网</Participant>
					<Denoter type="operation" did="d2">测定</Denoter>
				</Event>， 
				<Event eid="e3">
					<Time type="relTime" tid="t3">１１月１０日９时２２分</Time>，
					<Location lid="l3">青海省海西蒙古族藏族自治州大柴旦地区</Location>发生６．３级
					<Denoter type="emergency" did="d3">地震</Denoter>
				</Event>。
			</Sentence>  
			<Sentence> 
				<Event eid="e4">
					<Location lid="l4">西宁市、格尔木市等地</Location>有
					<Denoter type="emergency" did="d4">震感</Denoter>。
				</Event> 
			</Sentence> 
		</Paragraph>  
		<Paragraph> 
			<Sentence> 
				<Event eid="e5" type="thoughtevent">格尔木市委有关负责人
					<Participant sid="s5">罗正刚</Participant>
					<Denoter type="statement" did="d5">告诉</Denoter>
					<Participant oid="o5">记者</Participant>
				</Event>， 
				<Event eid="e6">
					<Location lid="l6">格尔木市区</Location>有明显
					<Denoter type="emergency" did="d6">震感</Denoter>
				</Event>， 
				<Event eid="e7">
					<Participant sid="s7,s8">市民</Participant>纷纷
					<Denoter type="movement" did="d7">跑</Denoter>出
					<Location type="origin" lid="l7">建筑物</Location>
				</Event>  
				<Event eid="e8">
					<Denoter type="operation" did="d8">避险</Denoter>
				</Event>。
			</Sentence> 
		</Paragraph>  
		<Paragraph> 
			<Sentence> 
				<Event eid="e9" type="thoughtevent">
					<Participant sid="s9">青海省地震局工作人员</Participant>
					<Denoter type="statement" did="d8">介绍</Denoter>
				</Event> ，此次震中坐标为北纬３７．６度，东经９５．９度，位于大柴旦东南方向，震源深度约１０公里。
			</Sentence>  
			<Sentence> 
				<Event polarity="negative" eid="e10">
					<Time type="relTime" tid="t10">目前</Time>尚未
					<Denoter type="action" did="d10">接到</Denoter>人员伤亡和其他损失
					<Object oid="o10">报告</Object>
				</Event>。
			</Sentence>  
			<Sentence> 
				<Event eid="e11">地震造成的
					<Object oid="o11">损失</Object>正在
					<Denoter type="operation" did="d11">调查</Denoter>中
				</Event>。
			</Sentence> 
		</Paragraph> 
	</Content>  
	<eRelation relType="Thoughtcontent" thoughtevent_eid="e1" thoughtcontent_eids="e2-e11"/>  
	<eRelation relType="Thoughtcontent" thoughtevent_eid="e2" thoughtcontent_eids="e3-e4"/>  
	<eRelation relType="Thoughtcontent" thoughtevent_eid="e5" thoughtcontent_eids="e6-e8"/>  
	<eRelation relType="Causal" cause_eid="e3" effect_eid="e4"/>  
	<eRelation relType="Causal" cause_eid="e6" effect_eid="e7"/>  
	<eRelation relType="Causal" cause_eid="e6" effect_eid="e8"/> 
</Body>
